single_source/__init__.py
single_source/errors.py
single_source/py.typed
single_source/version.py
single_source-0.4.0.dist-info/LICENSE
single_source-0.4.0.dist-info/METADATA
single_source-0.4.0.dist-info/WHEEL
single_source-0.4.0.dist-info/RECORD
