Metadata-Version: 2.1
Name: single-source
Version: 0.4.0
Summary: Access to the project version in Python code for PEP 621-style projects
Home-page: https://github.com/rabbit72/single-source
License: MIT
Keywords: pyproject,version,__version__,poetry,single source
Author: Daniil Shadrin
Author-email: rabbit72rus@gmail.com
Maintainer: Daniil Shadrin
Maintainer-email: rabbit72rus@gmail.com
Requires-Python: >=3.8,<4.0
Classifier: Intended Audience :: Developers
Classifier: License :: OSI Approved :: MIT License
Classifier: Operating System :: OS Independent
Classifier: Programming Language :: Python :: 3
Classifier: Programming Language :: Python :: 3.8
Classifier: Programming Language :: Python :: 3.9
Classifier: Programming Language :: Python :: 3.10
Classifier: Programming Language :: Python :: 3.11
Classifier: Programming Language :: Python :: 3.12
Classifier: Programming Language :: Python :: 3 :: Only
Classifier: Topic :: Software Development :: Libraries :: Python Modules
Project-URL: Bug Tracker, https://github.com/rabbit72/single-source/issues
Project-URL: Repository, https://github.com/rabbit72/single-source.git
